ajithapackage1/__init__.py
ajithapackage1/py.typed
ajithapackage1/_jsii/__init__.py
ajithapackage1/_jsii/ajithapackage1@0.0.23.jsii.tgz
ajithapackage1-0.0.23.dist-info/LICENSE
ajithapackage1-0.0.23.dist-info/METADATA
ajithapackage1-0.0.23.dist-info/WHEEL
ajithapackage1-0.0.23.dist-info/top_level.txt
ajithapackage1-0.0.23.dist-info/RECORD
